dig/__init__.py
dig/version.py
dig/ggraph/__init__.py
dig/ggraph/dataset/PygDataset.py
dig/ggraph/dataset/__init__.py
dig/ggraph/dataset/config.csv
dig/ggraph/dataset/ggraph_dataset.py
dig/ggraph/evaluation/__init__.py
dig/ggraph/evaluation/metric.py
dig/ggraph/method/__init__.py
dig/ggraph/method/generator.py
dig/ggraph/method/GraphAF/__init__.py
dig/ggraph/method/GraphAF/graphaf.py
dig/ggraph/method/GraphAF/train_utils.py
dig/ggraph/method/GraphAF/model/__init__.py
dig/ggraph/method/GraphAF/model/graphaf.py
dig/ggraph/method/GraphAF/model/graphflow.py
dig/ggraph/method/GraphAF/model/graphflow_con_rl.py
dig/ggraph/method/GraphAF/model/graphflow_rl.py
dig/ggraph/method/GraphAF/model/model_utils.py
dig/ggraph/method/GraphAF/model/rgcn.py
dig/ggraph/method/GraphAF/model/st_net.py
dig/ggraph/method/GraphDF/__init__.py
dig/ggraph/method/GraphDF/graphdf.py
dig/ggraph/method/GraphDF/train_utils.py
dig/ggraph/method/GraphDF/model/__init__.py
dig/ggraph/method/GraphDF/model/df_utils.py
dig/ggraph/method/GraphDF/model/disgraphaf.py
dig/ggraph/method/GraphDF/model/graphflow.py
dig/ggraph/method/GraphDF/model/graphflow_con_rl.py
dig/ggraph/method/GraphDF/model/graphflow_rl.py
dig/ggraph/method/GraphDF/model/rgcn.py
dig/ggraph/method/GraphDF/model/st_net.py
dig/ggraph/method/GraphEBM/__init__.py
dig/ggraph/method/GraphEBM/energy_func.py
dig/ggraph/method/GraphEBM/graphebm.py
dig/ggraph/method/GraphEBM/util.py
dig/ggraph/method/JTVAE/__init__.py
dig/ggraph/method/JTVAE/jtvae.py
dig/ggraph/method/JTVAE/fast_jtnn/__init__.py
dig/ggraph/method/JTVAE/fast_jtnn/chemutils.py
dig/ggraph/method/JTVAE/fast_jtnn/datautils.py
dig/ggraph/method/JTVAE/fast_jtnn/jtmpn.py
dig/ggraph/method/JTVAE/fast_jtnn/jtmpn_bo.py
dig/ggraph/method/JTVAE/fast_jtnn/jtnn_dec.py
dig/ggraph/method/JTVAE/fast_jtnn/jtnn_enc.py
dig/ggraph/method/JTVAE/fast_jtnn/jtnn_enc_bo.py
dig/ggraph/method/JTVAE/fast_jtnn/jtnn_vae.py
dig/ggraph/method/JTVAE/fast_jtnn/jtnn_vae_bo.py
dive_into_graphs-1.1.0.dist-info/LICENSE
dive_into_graphs-1.1.0.dist-info/METADATA
dive_into_graphs-1.1.0.dist-info/WHEEL
dive_into_graphs-1.1.0.dist-info/top_level.txt
dive_into_graphs-1.1.0.dist-info/RECORD
