Metadata-Version: 2.1
Name: dive-into-graphs
Version: 1.1.0
Summary: DIG: Dive into Graphs is a turnkey library for graph deep learning research.
Home-page: https://github.com/divelab/DIG
Author: DIVE Lab@TAMU
Author-email: sji@tamu.edu
Maintainer: DIVE Lab@TAMU
License: GPLv3
Classifier: Programming Language :: Python :: 3
Classifier: License :: OSI Approved :: GNU General Public License v3 (GPLv3)
Classifier: Operating System :: OS Independent
Requires-Python: >=3.6
License-File: LICENSE
Requires-Dist: scipy
Requires-Dist: cilog
Requires-Dist: typed-argument-parser (==1.7.2)
Requires-Dist: captum (==0.2.0)
Requires-Dist: munch
Requires-Dist: gdown
Requires-Dist: shap
Requires-Dist: IPython
Requires-Dist: tqdm
Requires-Dist: rdkit-pypi
Requires-Dist: pandas
Requires-Dist: sympy
Requires-Dist: pyscf (>=1.7.6)
Requires-Dist: hydra-core
Provides-Extra: test
Requires-Dist: pytest ; extra == 'test'
Requires-Dist: pytest-cov ; extra == 'test'
Requires-Dist: mock ; extra == 'test'
